to_naive_utc/__init__.py
to_naive_utc/to_naive_utc.py
to_naive_utc/to_timedelta.py
to_naive_utc-0.1.2.dist-info/METADATA
to_naive_utc-0.1.2.dist-info/WHEEL
to_naive_utc-0.1.2.dist-info/licenses/LICENSE
to_naive_utc-0.1.2.dist-info/RECORD
