Metadata-Version: 2.4
Name: to-naive-utc
Version: 0.1.2
Summary: Convert any datetime-like object in Python to naive UTC. No timezone - no problems
Author-email: Mark Lidenberg <marklidenberg@gmail.com>
License: MIT
License-File: LICENSE
Classifier: Intended Audience :: Developers
Classifier: License :: OSI Approved :: MIT License
Classifier: Programming Language :: Python :: 3
Classifier: Programming Language :: Python :: 3.8
Classifier: Programming Language :: Python :: 3.9
Classifier: Programming Language :: Python :: 3.10
Classifier: Programming Language :: Python :: 3.11
Classifier: Programming Language :: Python :: 3.12
Classifier: Programming Language :: Python :: 3.13
Requires-Python: >=3.8
Requires-Dist: python-dateutil>=2.9.0.post0
Provides-Extra: dev
Requires-Dist: arrow>=1.3.0; extra == 'dev'
Requires-Dist: build>=1.2.2.post1; extra == 'dev'
Requires-Dist: dony>=0.2.1; extra == 'dev'
Requires-Dist: numpy>=1.24.4; extra == 'dev'
Requires-Dist: pandas>=2.0.3; extra == 'dev'
Requires-Dist: pendulum>=3.0.0; extra == 'dev'
Requires-Dist: twine>=6.1.0; extra == 'dev'
